[
  {
    "review": "돌프영화를 감동으로 봤던 기억이.. 더불어 퍼니셔도.. 리틀도꾜도..   그당시 돌프룬드그렌 세상이었음...",
    "date": "15.05.23",
    "rating": "10",
    "author": "phn6****",
    "review_id": "9940242",
    "movie_id": "12121"
  },
  {
    "review": "과거엔 대단했을지 모르나 지금 보기엔 너무 유치하다. 그래도 8,90년대 액션영화 특유의 분위기를 느낄 수 있음.",
    "date": "14.06.22",
    "rating": "7",
    "author": "virt****",
    "review_id": "8847509",
    "movie_id": "12121"
  },
  {
    "review": "별로 재미 없는...지금 보면 3류삘이 너무 나는 ㅋㅋ",
    "date": "13.12.01",
    "rating": "1",
    "author": "newl****",
    "review_id": "8183854",
    "movie_id": "12121"
  },
  {
    "review": "정말 다시보고 싶은 영화!도대체가 어디서 다시 다운받을수있나요?ㅠㅠ 꼭 다시보고싶어요",
    "date": "13.09.01",
    "rating": "10",
    "author": "sksa****",
    "review_id": "7942041",
    "movie_id": "12121"
  },
  {
    "review": "중학교 2학년 청계천 세운상가 아세아극장에서 설레는 마음으로 본 기억이 ㅎㅎ 그 시절의 기억이 새록새록~~ 때론 이렇게 둔탁하고 묵직한 마초적인 8~90년대 액션영화가 더 보기좋다",
    "date": "13.08.23",
    "rating": "10",
    "author": "soof****",
    "review_id": "7915333",
    "movie_id": "12121"
  },
  {
    "review": "가볍게 즐길수있는 오락 액션영화",
    "