[
  {
    "review": "그 당시 영화임에도 불구하고 지금 액션에 꿀리지 않아.",
    "date": "15.08.23",
    "rating": "10",
    "author": "phan****",
    "review_id": "10269609",
    "movie_id": "36484"
  },
  {
    "review": "나도 감정이 없어지는 약 먹고 싶네...",
    "date": "15.08.18",
    "rating": "10",
    "author": "chee****",
    "review_id": "10249904",
    "movie_id": "36484"
  },
  {
    "review": "건카타 하나만으론 설명불가",
    "date": "15.08.16",
    "rating": "10",
    "author": "id17****",
    "review_id": "10243261",
    "movie_id": "36484"
  },
  {
    "review": "단연 최고의영화다.  평점이 왜이래 ㅡㅡ",
    "date": "15.08.14",
    "rating": "10",
    "author": "myz0****",
    "review_id": "10229518",
    "movie_id": "36484"
  },
  {
    "review": "Good good good",
    "date": "15.08.13",
    "rating": "10",
    "author": "ssk9****",
    "review_id": "10225293",
    "movie_id": "36484"
  },
  {
    "review": "나는 가난하여 가진게 꿈밖에 없기에, 내 꿈을 그대 발밑에 깔았습니다. 사뿐히 밟으소서, 그대 밟은것 내 꿈이오니.",
    "date": "15.08.10",
    "rating": "10",
    "author": "qkrq****",
    "review_id": "10214214",
    "movie_id": "36484"
  },
  {
    "review": "건 카타. 한 마디로 요약된다. 봐라.",
    "date": "15.08.05",
    "rating": "8",
    "author": "men5****",
    "review_id": "10186848",
    "movie_id": "36484"
  },
  {
    "review": "매트릭스랑 비슷한거같은대 전혀다른영화 개인적으론 매트릭스보다 더 재밌게봤었던영화",
    "date": "15.08.03",
    "rating": "10",
    "author": "yuei****",
    "review_id": "10181758",
    "movie_id": "36484"
  },
  {
    "review": "무조건 봐라. 건가타 조낸 머싰음",
    "date": "15.08.03",
    "rating": "10",
    "author": "andy****",
    "review_id": "10178592",
    "movie_id": "36484"
  },
  {
    "review": "더 올려야지 9점 이상 충분히 가능",
    "date": "15.08.02",
    "rating": "10",
    "author": "inwo****",
    "review_id": "10174901",
    "movie_id": "36484"
  },
  {
    "review": "그냥아무말도하지말고봐라",
    "date": "15.07.26",
    "rating": "10",
    "author": "leeq****",
    "review_id": "10145934",
    "movie_id": "36484"
  },
  {
    "review": "그렇게 감정싸움으로 인간세상은 전쟁으로 몰락하고만다",
    "date": "15.07.25",
    "rating": "9",
    "author": "chos****",
    "review_id": "10138962",
    "movie_id": "36484"
  },
  {
    "review": "완전 꿀잼 단순한 오락액션 영화가 아니다 이건 볼만한 가치가 충분하다 꼭보삼",
    "date": "15.07.16",
    "rating": "10",
    "author": "bbad****",
    "review_id": "10109936",
    "movie_id": "36484"
  },
  {
    "review": "건카타실제로도존재할려나",
    "date": "15.07.13",
    "rating": "10",
    "author": "6772****",
    "review_id": "10101590",
    "movie_id": "36484"
  },
  {
    "review": "말 할 필요가 없습니다!!",
    "date": "15.07.12",
    "rating": "10",
    "author": "alsr****",
    "review_id": "10095649",
    "movie_id": "36484"
  },
  {
    "review": "화려한 액션에 비해 설정구멍이 너무 크다",
    "date": "15.07.11",
    "rating": "3",
    "author": "ehdg****",
    "review_id": "10093830",
    "movie_id": "36484"
  },
  {
    "review": "개잼꿀잼 빅잼 핵잼 ㅅㅅ",
    "date": "15.07.08",
    "rating": "10",
    "author": "dbtl****",
    "review_id": "10080662",
    "movie_id": "36484"
  },
  {
    "review": "정말 여운이 남는 액션영화....진짜 괜찮다",
    "date": "15.07.05",
    "rating": "10",
    "author": "yuns****",
    "review_id": "10072618",
    "movie_id": "36484"
  },
  {
    "review": "잼씀다 약간 허술한점도 없지않아 쪼끔은 있었지만 잼게봤음..영화관에서 봤음 더 재밌었을것같아요지금봐도 안촌스럽 근데 진짜 울나라 버젼 포스터는...할말이 없음ㅋㅋㅋ",
    "date": "15.07.05",
    "rating": "10",
    "author": "spqj****",
    "review_id": "10071812",
    "movie_id": "36484"
  },
  {
    "review": "점수가 넘 낮다 이건 올려야겠다",
    "date": "15.07.05",
    "rating": "10",
    "author": "cyra****",
    "review_id": "10070591",
    "movie_id": "36484"
  },
  {
    "review": "이런 영화도 있었나 싶었는데... 감상 해보니 대~박 이네요",
    "date": "15.07.04",
    "rating": "10",
    "author": "alxn****",
    "review_id": "10067119",
    "movie_id": "36484"
  },
  {
    "review": "재밌음 엄청 재밌음 진짜 재밌음",
    "date": "15.07.03",
    "rating": "10",
    "author": "sh57****",
    "review_id": "10066263",
    "movie_id": "36484"
  },
  {
    "review": "평점  올리려고 10점 줌",
    "date": "15.06.28",
    "rating": "10",
    "author": "lysd****",
    "review_id": "10046328",
    "movie_id": "36484"
  },
  {
    "review": "단순 액션영화라기에는 저평가된듯 당시 메트릭스와 비교하며 마케팅을 했지만 메트릭스보다는 가타카와 비슷한 느낌을 받았다",
    "date": "15.06.25",
    "rating": "9",
    "author": "pcik****",
    "review_id": "10031774",
    "movie_id": "36484"
  },
  {
    "review": "인터넷에서 총씬 보고 과대평가된듯.. 영화나 보고 쓰는거냐?ㅋㅋ",
    "date": "15.06.24",
    "rating": "2",
    "author": "ccor****",
    "review_id": "10029526",
    "movie_id": "36484"
  },
  {
    "review": "2003년판 람보. 제목을 바꿔라. 총알을 안맞는 사나이로. 군인들도 초반엔 반군들 총에 절대 안맞더니 마지막엔 급하게 끝내려고 반군들 총에 줄줄이 눕는게 참 감동적이었다.",
    "date": "15.06.17",
    "rating": "5",
    "author": "drum****",
    "review_id": "10005434",
    "movie_id": "36484"
  },
  {
    "review": "와ㅔ 2003년꺼맞나?? 최근거인줄알앗네요.",
    "date": "15.06.16",
    "rating": "10",
    "author": "mjo3****",
    "review_id": "10003838",
    "movie_id": "36484"
  },
  {
    "review": "갠적으로 킹스맨보다 재밌었음",
    "date": "15.06.14",
    "rating": "10",
    "author": "evz1****",
    "review_id": "10000413",
    "movie_id": "36484"
  },
  {
    "review": "이 영화를 언젠가 잊게될때 다시 보고싶어서 스스로 족적을 남깁니다",
    "date": "15.06.13",
    "rating": "10",
    "author": "sosf****",
    "review_id": "9996135",
    "movie_id": "36484"
  },
  {
    "review": "인간은 감정이 없는게 더 좋을지도 모른다는 생각을 하게되는 영화",
    "date": "15.06.11",
    "rating": "10",
    "author": "quse****",
    "review_id": "9990515",
    "movie_id": "36484"
  },
  {
    "review": "마무리가아쉽다...",
    "date": "15.06.11",
    "rating": "8",
    "author": "m960****",
    "review_id": "9990442",
    "movie_id": "36484"
  },
  {
    "review": "베일 외모 너무 사기다. 토레스랑 많이 닮았ㅇ",
    "date": "15.06.09",
    "rating": "9",
    "author": "beat****",
    "review_id": "9986188",
    "movie_id": "36484"
  },
  {
    "review": "감정은 부차적인 문제, 자유가 아니면 죽음을 달라",
    "date": "15.06.09",
    "rating": "9",
    "author": "mins****",
    "review_id": "9985830",
    "movie_id": "36484"
  },
  {
    "review": "마무리가 너무 다급해서 아쉬웠지만, 많은 여운이 남는 영화",
    "date": "15.06.08",
    "rating": "10",
    "author": "swee****",
    "review_id": "9984750",
    "m