[
  {
    "review_id": "9863754",
    "movie_id": "95217",
    "author": "star****",
    "review": "에잇! 빌어먹을 홍우진!!!",
    "rating": "1",
    "date": "15.04.24"
  },
  {
    "review_id": "9723640",
    "movie_id": "95217",
    "author": "fpdl****",
    "review": "다섯손가락=막장 드라마의 표본",
    "rating": "1",
    "date": "15.02.21"
  },
  {
    "review_id": "9462881",
    "movie_id": "95217",
    "author": "pcu7****",
    "review": "답답한게ㅋㅋㅋㅋ왜주지훈은왜자기방단속을안할까ㅋㄱㅋ상황전개를너무허술하게하셧네",
    "rating": "5",
    "date": "14.12.10"
  },
  {
    "review_id": "9399542",
    "movie_id": "95217",
    "author": "dbwl****",
    "review": "정말 너무 많이 울었습니다 모성애가 무엇인지 알게한..또 인생을 좌우하는 한순간의 일들..너무 많은 것을 깨닫게 해 준 드라마 정말 평생 두고두고 잊지 못할 것 같습니다 ㅠㅠ마지막화에서 정말 한달치 눈물을 쏟았네요배우 채시라님의 연기에 박수를!",
    "rating": "10",
    "date": "14.11.19"
  },
  {
    "review_id": "9339540",
    "movie_id": "95217",
    "author": "seo6****",